{"Id":"013e7cc3-ac42-4a9c-a8db-12d3996fa10c","LogDateUtc":"2016-09-03T18:46:05.3985382Z","IpAddress":"127.0.0.1","Culture":"en-US","Url":"/blog","ShortUrl":"/blog","Thread":"","LogLevel":"Information","Logger":"Microsoft.AspNetCore.Mvc.ViewFeatures.Internal.ViewResultExecutor","Message":"Executing ViewResult, running view at path /Views/Blog/Index.cshtml.","StateJson":"[{\"Key\":\"Path\",\"Value\":\"/Views/Blog/Index.cshtml\"},{\"Key\":\"{OriginalFormat}\",\"Value\":\"Executing ViewResult, running view at path {Path}.\"}]","EventId":1}