{"Id":"35ef4ee6-e762-4c98-9a5c-09bea4d2b7ca","LogDateUtc":"2016-09-03T19:32:11.8145839Z","IpAddress":"127.0.0.1","Culture":"en-US","Url":"/cscsr/jqueryvalidationunobtrusive","ShortUrl":"/cscsr/jqueryvalidationunobtrusive","Thread":"","LogLevel":"Information","Logger":"Microsoft.AspNetCore.Mvc.Internal.ControllerActionInvoker","Message":"Executed action cloudscribe.Core.Web.Controllers.cscsrController.jqueryvalidationunobtrusive (cloudscribe.Core.Web) in 11.5019ms","StateJson":"[{\"Key\":\"ActionName\",\"Value\":\"cloudscribe.Core.Web.Controllers.cscsrController.jqueryvalidationunobtrusive (cloudscribe.Core.Web)\"},{\"Key\":\"ElapsedMilliseconds\",\"Value\":11.501900000000001},{\"Key\":\"{OriginalFormat}\",\"Value\":\"Executed action {ActionName} in {ElapsedMilliseconds}ms\"}]","EventId":2}