{"Id":"3eeb1c6f-9e74-4964-9db8-f8f54e9ad1ae","LogDateUtc":"2016-09-03T13:49:23.6405642Z","IpAddress":"127.0.0.1","Culture":"en-US","Url":"/blog/category/foo","ShortUrl":"/blog/category/foo","Thread":"","LogLevel":"Information","Logger":"Microsoft.AspNetCore.Authorization.DefaultAuthorizationService","Message":"Authorization was successful for user: admin.","StateJson":"[{\"Key\":\"UserName\",\"Value\":\"admin\"},{\"Key\":\"{OriginalFormat}\",\"Value\":\"Authorization was successful for user: {UserName}.\"}]","EventId":1}