{"Id":"59582d37-2e62-4656-ba17-796df98aa673","LogDateUtc":"2016-09-03T13:26:37.2262964Z","IpAddress":"127.0.0.1","Culture":"en-US","Url":"/csscsr/editorjs","ShortUrl":"/csscsr/editorjs","Thread":"","LogLevel":"Information","Logger":"Microsoft.AspNetCore.Authentication.Cookies.CookieAuthenticationMiddleware","Message":"HttpContext.User merged via AutomaticAuthentication from authenticationScheme: Application-.","StateJson":"[{\"Key\":\"AuthenticationScheme\",\"Value\":\"Application-\"},{\"Key\":\"{OriginalFormat}\",\"Value\":\"HttpContext.User merged via AutomaticAuthentication from authenticationScheme: {AuthenticationScheme}.\"}]","EventId":3}