{"Id":"66f05589-d4fd-4e41-9633-506729cc3921","LogDateUtc":"2016-09-03T15:20:02.0906009Z","IpAddress":"127.0.0.1","Culture":"en-US","Url":"/csscsr/jqueryhotkeys","ShortUrl":"/csscsr/jqueryhotkeys","Thread":"","LogLevel":"Information","Logger":"Microsoft.AspNetCore.Mvc.Internal.ControllerActionInvoker","Message":"Executed action cloudscribe.SimpleContent.Web.Controllers.csscsrController.jqueryhotkeys (cloudscribe.SimpleContent.Web) in 21.8993ms","StateJson":"[{\"Key\":\"ActionName\",\"Value\":\"cloudscribe.SimpleContent.Web.Controllers.csscsrController.jqueryhotkeys (cloudscribe.SimpleContent.Web)\"},{\"Key\":\"ElapsedMilliseconds\",\"Value\":21.8993},{\"Key\":\"{OriginalFormat}\",\"Value\":\"Executed action {ActionName} in {ElapsedMilliseconds}ms\"}]","EventId":2}