{"Id":"683d7a0b-ed07-4a13-8939-b835ee1ed23e","LogDateUtc":"2016-09-03T13:26:32.5567044Z","IpAddress":"127.0.0.1","Culture":"en-US","Url":"/csscsr/bootstrapwysiwygjs","ShortUrl":"/csscsr/bootstrapwysiwygjs","Thread":"","LogLevel":"Information","Logger":"Microsoft.AspNetCore.Authentication.Cookies.CookieAuthenticationMiddleware","Message":"HttpContext.User merged via AutomaticAuthentication from authenticationScheme: Application-.","StateJson":"[{\"Key\":\"AuthenticationScheme\",\"Value\":\"Application-\"},{\"Key\":\"{OriginalFormat}\",\"Value\":\"HttpContext.User merged via AutomaticAuthentication from authenticationScheme: {AuthenticationScheme}.\"}]","EventId":3}