{"Id":"77b03d9c-354f-4420-8348-6affa9f2ab2c","LogDateUtc":"2016-09-03T13:49:23.7265663Z","IpAddress":"127.0.0.1","Culture":"en-US","Url":"/csscsr/contentadmincss","ShortUrl":"/csscsr/contentadmincss","Thread":"","LogLevel":"Information","Logger":"Microsoft.AspNetCore.Mvc.Internal.ControllerActionInvoker","Message":"Executed action cloudscribe.SimpleContent.Web.Controllers.csscsrController.contentadmincss (cloudscribe.SimpleContent.Web) in 26.5555ms","StateJson":"[{\"Key\":\"ActionName\",\"Value\":\"cloudscribe.SimpleContent.Web.Controllers.csscsrController.contentadmincss (cloudscribe.SimpleContent.Web)\"},{\"Key\":\"ElapsedMilliseconds\",\"Value\":26.555500000000002},{\"Key\":\"{OriginalFormat}\",\"Value\":\"Executed action {ActionName} in {ElapsedMilliseconds}ms\"}]","EventId":2}