{"Id":"7b9ef339-8ae7-4f10-88e4-7e798a1336cb","LogDateUtc":"2016-09-03T13:53:46.34594Z","IpAddress":"127.0.0.1","Culture":"en-US","Url":"/csscsr/jqueryhotkeys","ShortUrl":"/csscsr/jqueryhotkeys","Thread":"","LogLevel":"Information","Logger":"Microsoft.AspNetCore.Authentication.Cookies.CookieAuthenticationMiddleware","Message":"HttpContext.User merged via AutomaticAuthentication from authenticationScheme: Application-.","StateJson":"[{\"Key\":\"AuthenticationScheme\",\"Value\":\"Application-\"},{\"Key\":\"{OriginalFormat}\",\"Value\":\"HttpContext.User merged via AutomaticAuthentication from authenticationScheme: {AuthenticationScheme}.\"}]","EventId":3}