{"Id":"8befc79f-4878-4a4f-8ea8-b23f33085af8","LogDateUtc":"2016-09-03T15:18:51.0837248Z","IpAddress":"127.0.0.1","Culture":"en-US","Url":"/csscsr/blogcommoncss","ShortUrl":"/csscsr/blogcommoncss","Thread":"","LogLevel":"Information","Logger":"Microsoft.AspNetCore.Authentication.Cookies.CookieAuthenticationMiddleware","Message":"HttpContext.User merged via AutomaticAuthentication from authenticationScheme: Application-.","StateJson":"[{\"Key\":\"AuthenticationScheme\",\"Value\":\"Application-\"},{\"Key\":\"{OriginalFormat}\",\"Value\":\"HttpContext.User merged via AutomaticAuthentication from authenticationScheme: {AuthenticationScheme}.\"}]","EventId":3}