{"Id":"921fe10e-69b5-4abb-86c9-0b87b5e3f155","LogDateUtc":"2016-09-03T13:49:46.0195674Z","IpAddress":"127.0.0.1","Culture":"en-US","Url":"/csscsr/jquerycookie","ShortUrl":"/csscsr/jquerycookie","Thread":"","LogLevel":"Information","Logger":"Microsoft.AspNetCore.Authentication.Cookies.CookieAuthenticationMiddleware","Message":"HttpContext.User merged via AutomaticAuthentication from authenticationScheme: Application-.","StateJson":"[{\"Key\":\"AuthenticationScheme\",\"Value\":\"Application-\"},{\"Key\":\"{OriginalFormat}\",\"Value\":\"HttpContext.User merged via AutomaticAuthentication from authenticationScheme: {AuthenticationScheme}.\"}]","EventId":3}