{"Id":"a2f76f55-5730-4bfa-bf6d-d6ad8b91e4b3","LogDateUtc":"2016-09-03T18:45:36.0444965Z","IpAddress":"127.0.0.1","Culture":"en-US","Url":"/cscsr/sidemenu","ShortUrl":"/cscsr/sidemenu","Thread":"","LogLevel":"Information","Logger":"Microsoft.AspNetCore.Authentication.Cookies.CookieAuthenticationMiddleware","Message":"HttpContext.User merged via AutomaticAuthentication from authenticationScheme: Application-.","StateJson":"[{\"Key\":\"AuthenticationScheme\",\"Value\":\"Application-\"},{\"Key\":\"{OriginalFormat}\",\"Value\":\"HttpContext.User merged via AutomaticAuthentication from authenticationScheme: {AuthenticationScheme}.\"}]","EventId":3}