{"Id":"b541727c-de2e-42cb-b9c2-4227601d2214","LogDateUtc":"2016-09-03T13:26:19.8063207Z","IpAddress":"127.0.0.1","Culture":"en-US","Url":"/csscsr/jquerycookie","ShortUrl":"/csscsr/jquerycookie","Thread":"","LogLevel":"Information","Logger":"Microsoft.AspNetCore.Mvc.Internal.ControllerActionInvoker","Message":"Executed action cloudscribe.SimpleContent.Web.Controllers.csscsrController.jquerycookie (cloudscribe.SimpleContent.Web) in 36.7288ms","StateJson":"[{\"Key\":\"ActionName\",\"Value\":\"cloudscribe.SimpleContent.Web.Controllers.csscsrController.jquerycookie (cloudscribe.SimpleContent.Web)\"},{\"Key\":\"ElapsedMilliseconds\",\"Value\":36.7288},{\"Key\":\"{OriginalFormat}\",\"Value\":\"Executed action {ActionName} in {ElapsedMilliseconds}ms\"}]","EventId":2}