{"Id":"b996fc40-9a8a-4226-ab0b-b584309e2e16","LogDateUtc":"2016-09-03T18:45:46.5546479Z","IpAddress":"127.0.0.1","Culture":"en-US","Url":"/csscsr/jqueryhotkeys","ShortUrl":"/csscsr/jqueryhotkeys","Thread":"","LogLevel":"Information","Logger":"Microsoft.AspNetCore.Mvc.ContentResult","Message":"Executing ContentResult with HTTP Response ContentType of text/javascript","StateJson":"[{\"Key\":\"ContentType\",\"Value\":\"text/javascript\"},{\"Key\":\"{OriginalFormat}\",\"Value\":\"Executing ContentResult with HTTP Response ContentType of {ContentType}\"}]","EventId":1}