{"Id":"bdc938fc-6f4c-4d57-833b-9dd0b1859c4f","LogDateUtc":"2016-09-03T19:38:53.6494635Z","IpAddress":"127.0.0.1","Culture":"en-US","Url":"/csscsr/momentwithlocalesjs","ShortUrl":"/csscsr/momentwithlocalesjs","Thread":"","LogLevel":"Information","Logger":"Microsoft.AspNetCore.Mvc.Internal.ControllerActionInvoker","Message":"Executed action cloudscribe.SimpleContent.Web.Controllers.csscsrController.momentwithlocalesjs (cloudscribe.SimpleContent.Web) in 23.5087ms","StateJson":"[{\"Key\":\"ActionName\",\"Value\":\"cloudscribe.SimpleContent.Web.Controllers.csscsrController.momentwithlocalesjs (cloudscribe.SimpleContent.Web)\"},{\"Key\":\"ElapsedMilliseconds\",\"Value\":23.5087},{\"Key\":\"{OriginalFormat}\",\"Value\":\"Executed action {ActionName} in {ElapsedMilliseconds}ms\"}]","EventId":2}