{"Id":"50f04aa7-3511-42e2-8eac-cc2b094ba01c","LogDateUtc":"2016-09-02T19:10:06.5763238Z","IpAddress":"127.0.0.1","Culture":"en-US","Url":"/ContentSettings/Index","ShortUrl":"/ContentSettings/Index","Thread":"","LogLevel":"Information","Logger":"Microsoft.AspNetCore.Authorization.DefaultAuthorizationService","Message":"Authorization was successful for user: admin.","StateJson":"[{\"Key\":\"UserName\",\"Value\":\"admin\"},{\"Key\":\"{OriginalFormat}\",\"Value\":\"Authorization was successful for user: {UserName}.\"}]","EventId":1}