{"Id":"85962800-809e-4239-bbb9-492da3b42c35","LogDateUtc":"2016-09-02T19:40:06.0842311Z","IpAddress":"127.0.0.1","Culture":"en-US","Url":"/csscsr/jquerycookie","ShortUrl":"/csscsr/jquerycookie","Thread":"","LogLevel":"Information","Logger":"Microsoft.AspNetCore.Mvc.Internal.ControllerActionInvoker","Message":"Executed action cloudscribe.SimpleContent.Web.Controllers.csscsrController.jquerycookie (cloudscribe.SimpleContent.Web) in 15.8633ms","StateJson":"[{\"Key\":\"ActionName\",\"Value\":\"cloudscribe.SimpleContent.Web.Controllers.csscsrController.jquerycookie (cloudscribe.SimpleContent.Web)\"},{\"Key\":\"ElapsedMilliseconds\",\"Value\":15.8633},{\"Key\":\"{OriginalFormat}\",\"Value\":\"Executed action {ActionName} in {ElapsedMilliseconds}ms\"}]","EventId":2}