{"Id":"c86f6d2a-3d90-442e-8b9e-e39665c12125","LogDateUtc":"2016-09-02T19:39:38.6607528Z","IpAddress":"127.0.0.1","Culture":"en-US","Url":"/csscsr/contentadmincss","ShortUrl":"/csscsr/contentadmincss","Thread":"","LogLevel":"Information","Logger":"Microsoft.AspNetCore.Mvc.ContentResult","Message":"Executing ContentResult with HTTP Response ContentType of text/css","StateJson":"[{\"Key\":\"ContentType\",\"Value\":\"text/css\"},{\"Key\":\"{OriginalFormat}\",\"Value\":\"Executing ContentResult with HTTP Response ContentType of {ContentType}\"}]","EventId":1}