{"Id":"d7e51e68-7208-4de2-ad20-75e48e2d0b55","LogDateUtc":"2016-09-02T19:44:07.20187Z","IpAddress":"127.0.0.1","Culture":"en-US","Url":"/csscsr/bootstrapdatetimepickercss","ShortUrl":"/csscsr/bootstrapdatetimepickercss","Thread":"","LogLevel":"Information","Logger":"Microsoft.AspNetCore.Mvc.ContentResult","Message":"Executing ContentResult with HTTP Response ContentType of text/css","StateJson":"[{\"Key\":\"ContentType\",\"Value\":\"text/css\"},{\"Key\":\"{OriginalFormat}\",\"Value\":\"Executing ContentResult with HTTP Response ContentType of {ContentType}\"}]","EventId":1}