{"Id":"055f9137-7631-4ec3-beb4-ebe17f5ea965","LogDateUtc":"2016-08-31T11:50:41.9027467Z","IpAddress":"127.0.0.1","Culture":"en-US","Url":"/csscsr/bootstrapdatetimepickercss","ShortUrl":"/csscsr/bootstrapdatetimepickercss","Thread":"","LogLevel":"Information","Logger":"Microsoft.AspNetCore.Mvc.ContentResult","Message":"Executing ContentResult with HTTP Response ContentType of text/css","StateJson":"[{\"Key\":\"ContentType\",\"Value\":\"text/css\"},{\"Key\":\"{OriginalFormat}\",\"Value\":\"Executing ContentResult with HTTP Response ContentType of {ContentType}\"}]","EventId":1}