{"Id":"09ce4157-37ba-4317-a1e6-d508518016c2","LogDateUtc":"2016-08-31T12:09:53.0295644Z","IpAddress":"127.0.0.1","Culture":"en-US","Url":"/","ShortUrl":"/","Thread":"","LogLevel":"Information","Logger":"Microsoft.AspNetCore.Session.DistributedSession","Message":"Session started; Key:110479b6-20e4-86bb-8b65-0f86605dfb98, Id:fd11661a-3ce0-7761-054d-70b49d7e85b9","StateJson":"[{\"Key\":\"sessionKey\",\"Value\":\"110479b6-20e4-86bb-8b65-0f86605dfb98\"},{\"Key\":\"sessionId\",\"Value\":\"fd11661a-3ce0-7761-054d-70b49d7e85b9\"},{\"Key\":\"{OriginalFormat}\",\"Value\":\"Session started; Key:{sessionKey}, Id:{sessionId}\"}]","EventId":3}