{"Id":"1bf6eceb-6ff1-4761-9d1f-e2c71274e1e1","LogDateUtc":"2016-08-31T11:46:09.8623843Z","IpAddress":"127.0.0.1","Culture":"en-US","Url":"/Page/AjaxPost","ShortUrl":"/Page/AjaxPost","Thread":"","LogLevel":"Information","Logger":"Microsoft.AspNetCore.Authorization.DefaultAuthorizationService","Message":"Authorization was successful for user: admin.","StateJson":"[{\"Key\":\"UserName\",\"Value\":\"admin\"},{\"Key\":\"{OriginalFormat}\",\"Value\":\"Authorization was successful for user: {UserName}.\"}]","EventId":1}