{"Id":"42c7454d-6136-41c6-8597-a873191826c8","LogDateUtc":"2016-08-31T11:46:10.0073868Z","IpAddress":"127.0.0.1","Culture":"en-US","Url":"/csscsr/bootstrapdatetimepickercss","ShortUrl":"/csscsr/bootstrapdatetimepickercss","Thread":"","LogLevel":"Information","Logger":"Microsoft.AspNetCore.Mvc.Internal.ControllerActionInvoker","Message":"Executed action cloudscribe.SimpleContent.Web.Controllers.csscsrController.bootstrapdatetimepickercss (cloudscribe.SimpleContent.Web) in 17.1437ms","StateJson":"[{\"Key\":\"ActionName\",\"Value\":\"cloudscribe.SimpleContent.Web.Controllers.csscsrController.bootstrapdatetimepickercss (cloudscribe.SimpleContent.Web)\"},{\"Key\":\"ElapsedMilliseconds\",\"Value\":17.1437},{\"Key\":\"{OriginalFormat}\",\"Value\":\"Executed action {ActionName} in {ElapsedMilliseconds}ms\"}]","EventId":2}