{"Id":"87aa2214-b2fe-4505-8fae-ddee0fba0ca2","LogDateUtc":"2016-08-31T11:46:09.9363853Z","IpAddress":"127.0.0.1","Culture":"en-US","Url":"/Page/Index","ShortUrl":"/Page/Index","Thread":"","LogLevel":"Information","Logger":"Microsoft.AspNetCore.Authorization.DefaultAuthorizationService","Message":"Authorization was successful for user: admin.","StateJson":"[{\"Key\":\"UserName\",\"Value\":\"admin\"},{\"Key\":\"{OriginalFormat}\",\"Value\":\"Authorization was successful for user: {UserName}.\"}]","EventId":1}