{"Id":"9b183a0f-0a84-42c6-afef-1d82ff02c901","LogDateUtc":"2016-08-31T11:45:52.4758551Z","IpAddress":"127.0.0.1","Culture":"en-US","Url":"/csscsr/jqueryhotkeys","ShortUrl":"/csscsr/jqueryhotkeys","Thread":"","LogLevel":"Information","Logger":"Microsoft.AspNetCore.Mvc.Internal.ControllerActionInvoker","Message":"Executed action cloudscribe.SimpleContent.Web.Controllers.csscsrController.jqueryhotkeys (cloudscribe.SimpleContent.Web) in 21.7705ms","StateJson":"[{\"Key\":\"ActionName\",\"Value\":\"cloudscribe.SimpleContent.Web.Controllers.csscsrController.jqueryhotkeys (cloudscribe.SimpleContent.Web)\"},{\"Key\":\"ElapsedMilliseconds\",\"Value\":21.770500000000002},{\"Key\":\"{OriginalFormat}\",\"Value\":\"Executed action {ActionName} in {ElapsedMilliseconds}ms\"}]","EventId":2}