{"Id":"ol-import","ProjectId":"f83067b4-919d-4910-acd1-4b3b1c210ecf","ParentId":"0","ParentSlug":"","PageOrder":17,"Title":"Ol Import","Author":"Admin","Slug":"ol-import","ExternalUrl":null,"CorrelationKey":null,"MetaDescription":null,"MetaJson":null,"MetaHtml":null,"Content":"<p>from the past</p>\r\n","PubDate":"2019-03-14T20:19:21.2121Z","LastModified":"2019-03-18T20:19:29.0793196Z","IsPublished":true,"MenuOnly":false,"ShowMenu":false,"ViewRoles":null,"Categories":[],"Comments":[],"ShowHeading":true,"ShowPubDate":false,"ShowLastModified":false,"ShowCategories":false,"ShowComments":false,"MenuFilters":null,"DisableEditor":false,"Resources":[],"ContentType":"html","CreatedUtc":"2019-03-18T20:19:28.9793015Z","CreatedByUser":"admin","LastModifiedByUser":"admin","DraftContent":null,"DraftAuthor":null,"DraftPubDate":null,"TemplateKey":null,"SerializedModel":null,"DraftSerializedModel":null,"Serializer":null}