<?xml version="1.0" encoding="utf-16"?>
<post>
  <id>its-been-a-long-time</id>
  <title>Its been a long time</title>
  <slug>its-been-a-long-time</slug>
  <correlationkey />
  <author>site2admin</author>
  <pubDate>2018-06-19T17:57:00.0000000Z</pubDate>
  <lastModified>2018-06-19T17:58:08.4684610Z</lastModified>
  <excerpt />
  <content>&lt;p&gt;It has been a long time since I posted here.&lt;/p&gt;

&lt;p&gt;&lt;img alt="" src="/two/arlo1-ws.jpg" style="width: 550px; height: 309px;" /&gt;&lt;/p&gt;
</content>
  <contentType>html</contentType>
  <imageUrl />
  <thumbnailUrl />
  <ispublished>true</ispublished>
  <isFeatured>false</isFeatured>
  <teaserOverride />
  <suppressTeaser>false</suppressTeaser>
  <categories></categories>
  <comments></comments>
</post>