{"Id":"1d27db04-8c0a-416e-b4cc-d0c3a243da30","LogDateUtc":"2016-09-08T15:49:33.0095221Z","IpAddress":"127.0.0.1","Culture":"en-US","Url":"/ContentSettings/Index","ShortUrl":"/ContentSettings/Index","Thread":"","LogLevel":"Information","Logger":"Microsoft.AspNetCore.Authorization.DefaultAuthorizationService","Message":"Authorization was successful for user: admin.","StateJson":"[{\"Key\":\"UserName\",\"Value\":\"admin\"},{\"Key\":\"{OriginalFormat}\",\"Value\":\"Authorization was successful for user: {UserName}.\"}]","EventId":1}