{"Id":"a8ef7519-fa73-46b0-92f3-73dd7d88e50b","LogDateUtc":"2016-09-08T12:28:29.6278366Z","IpAddress":"127.0.0.1","Culture":"en-US","Url":"/","ShortUrl":"/","Thread":"","LogLevel":"Information","Logger":"Microsoft.AspNetCore.Mvc.Internal.ControllerActionInvoker","Message":"Executed action cloudscribe.SimpleContent.Web.Controllers.PageController.Index (cloudscribe.SimpleContent.Web) in 34.7593ms","StateJson":"[{\"Key\":\"ActionName\",\"Value\":\"cloudscribe.SimpleContent.Web.Controllers.PageController.Index (cloudscribe.SimpleContent.Web)\"},{\"Key\":\"ElapsedMilliseconds\",\"Value\":34.7593},{\"Key\":\"{OriginalFormat}\",\"Value\":\"Executed action {ActionName} in {ElapsedMilliseconds}ms\"}]","EventId":2}