{"Id":"fb9f996e-7f25-4f1d-bf34-5ba8e44e7188","LogDateUtc":"2016-09-08T13:31:46.156765Z","IpAddress":"127.0.0.1","Culture":"en-US","Url":"/csscsr/bootstrapwysiwygjs","ShortUrl":"/csscsr/bootstrapwysiwygjs","Thread":"","LogLevel":"Information","Logger":"Microsoft.AspNetCore.Mvc.Internal.ControllerActionInvoker","Message":"Executed action cloudscribe.SimpleContent.Web.Controllers.csscsrController.bootstrapwysiwygjs (cloudscribe.SimpleContent.Web) in 38.6061ms","StateJson":"[{\"Key\":\"ActionName\",\"Value\":\"cloudscribe.SimpleContent.Web.Controllers.csscsrController.bootstrapwysiwygjs (cloudscribe.SimpleContent.Web)\"},{\"Key\":\"ElapsedMilliseconds\",\"Value\":38.606100000000005},{\"Key\":\"{OriginalFormat}\",\"Value\":\"Executed action {ActionName} in {ElapsedMilliseconds}ms\"}]","EventId":2}