{"Id":"2ac0cd68-49c0-4e17-a29a-78bbce549c48","LogDateUtc":"2016-09-13T20:09:18.0224079Z","IpAddress":"127.0.0.1","Culture":"en-US","Url":"/SiteAdmin/SiteInfo","ShortUrl":"/SiteAdmin/SiteInfo","Thread":"","LogLevel":"Information","Logger":"Microsoft.AspNetCore.Mvc.Internal.ControllerActionInvoker","Message":"Executed action cloudscribe.Core.Web.Controllers.SiteAdminController.SiteInfo (cloudscribe.Core.Web) in 1552.0324ms","StateJson":"[{\"Key\":\"ActionName\",\"Value\":\"cloudscribe.Core.Web.Controllers.SiteAdminController.SiteInfo (cloudscribe.Core.Web)\"},{\"Key\":\"ElapsedMilliseconds\",\"Value\":1552.0324},{\"Key\":\"{OriginalFormat}\",\"Value\":\"Executed action {ActionName} in {ElapsedMilliseconds}ms\"}]","EventId":2}