{"Id":"4e89c928-ca39-4cd0-82b0-58aa0331c40a","LogDateUtc":"2016-09-13T12:43:45.1442945Z","IpAddress":"127.0.0.1","Culture":"en-US","Url":"/csscsr/momentwithlocalesjs","ShortUrl":"/csscsr/momentwithlocalesjs","Thread":"","LogLevel":"Information","Logger":"Microsoft.AspNetCore.Mvc.Internal.ControllerActionInvoker","Message":"Executed action cloudscribe.SimpleContent.Web.Controllers.csscsrController.momentwithlocalesjs (cloudscribe.SimpleContent.Web) in 21.6215ms","StateJson":"[{\"Key\":\"ActionName\",\"Value\":\"cloudscribe.SimpleContent.Web.Controllers.csscsrController.momentwithlocalesjs (cloudscribe.SimpleContent.Web)\"},{\"Key\":\"ElapsedMilliseconds\",\"Value\":21.6215},{\"Key\":\"{OriginalFormat}\",\"Value\":\"Executed action {ActionName} in {ElapsedMilliseconds}ms\"}]","EventId":2}