{"Id":"ab933e0e-6bac-4850-afba-2aa5d2975e14","LogDateUtc":"2016-09-13T16:57:45.0164918Z","IpAddress":"127.0.0.1","Culture":"en-US","Url":"/SiteAdmin/SiteInfo","ShortUrl":"/SiteAdmin/SiteInfo","Thread":"","LogLevel":"Information","Logger":"Microsoft.AspNetCore.Mvc.ViewFeatures.Internal.ViewResultExecutor","Message":"Executing ViewResult, running view at path /Views/Sys/SiteAdmin/SiteInfo.cshtml.","StateJson":"[{\"Key\":\"Path\",\"Value\":\"/Views/Sys/SiteAdmin/SiteInfo.cshtml\"},{\"Key\":\"{OriginalFormat}\",\"Value\":\"Executing ViewResult, running view at path {Path}.\"}]","EventId":1}