{"Id":"c2e2f1af-0e2f-482d-97db-9cce65bd936c","LogDateUtc":"2016-09-13T12:44:46.2073933Z","IpAddress":"127.0.0.1","Culture":"en-US","Url":"/csscsr/editorjs","ShortUrl":"/csscsr/editorjs","Thread":"","LogLevel":"Information","Logger":"Microsoft.AspNetCore.Mvc.Internal.ControllerActionInvoker","Message":"Executed action cloudscribe.SimpleContent.Web.Controllers.csscsrController.editorjs (cloudscribe.SimpleContent.Web) in 17.3357ms","StateJson":"[{\"Key\":\"ActionName\",\"Value\":\"cloudscribe.SimpleContent.Web.Controllers.csscsrController.editorjs (cloudscribe.SimpleContent.Web)\"},{\"Key\":\"ElapsedMilliseconds\",\"Value\":17.3357},{\"Key\":\"{OriginalFormat}\",\"Value\":\"Executed action {ActionName} in {ElapsedMilliseconds}ms\"}]","EventId":2}