{"Id":"0d3bccdc-6832-41e4-8a3c-f1dc167ed85c","LogDateUtc":"2016-09-08T12:28:27.225072Z","IpAddress":"127.0.0.1","Culture":"en-US","Url":"/Home/Error/404","ShortUrl":"/Home/Error/404","Thread":"","LogLevel":"Warning","Logger":"example.WebApp.Controllers.HomeController","Message":"handled 404 for url: /lib/font-awesome/css/font-awesome.min.css","StateJson":"[{\"Key\":\"OriginalPath\",\"Value\":\"/lib/font-awesome/css/font-awesome.min.css\"},{\"Key\":\"{OriginalFormat}\",\"Value\":\"handled 404 for url: {OriginalPath}\"}]","EventId":0}