{"Id":"07843231-191c-4cdd-9924-b2893b623349","LogDateUtc":"2016-08-30T15:01:52.5832636Z","IpAddress":"127.0.0.1","Culture":"en-US","Url":"/csscsr/momentwithlocalesjs","ShortUrl":"/csscsr/momentwithlocalesjs","Thread":"","LogLevel":"Information","Logger":"Microsoft.AspNetCore.Mvc.Internal.ControllerActionInvoker","Message":"Executed action cloudscribe.SimpleContent.Web.Controllers.csscsrController.momentwithlocalesjs (cloudscribe.SimpleContent.Web) in 30.2819ms","StateJson":"[{\"Key\":\"ActionName\",\"Value\":\"cloudscribe.SimpleContent.Web.Controllers.csscsrController.momentwithlocalesjs (cloudscribe.SimpleContent.Web)\"},{\"Key\":\"ElapsedMilliseconds\",\"Value\":30.2819},{\"Key\":\"{OriginalFormat}\",\"Value\":\"Executed action {ActionName} in {ElapsedMilliseconds}ms\"}]","EventId":2}