{"Id":"16a6bd23-6b42-41dd-ac12-8decfac43994","LogDateUtc":"2016-08-30T15:01:59.976985Z","IpAddress":"127.0.0.1","Culture":"en-US","Url":"/Page/Index","ShortUrl":"/Page/Index","Thread":"","LogLevel":"Information","Logger":"Microsoft.AspNetCore.Authorization.DefaultAuthorizationService","Message":"Authorization was successful for user: admin.","StateJson":"[{\"Key\":\"UserName\",\"Value\":\"admin\"},{\"Key\":\"{OriginalFormat}\",\"Value\":\"Authorization was successful for user: {UserName}.\"}]","EventId":1}