{"Id":"5380c2b3-8abd-4d2b-9e10-8539cf088299","LogDateUtc":"2016-08-30T18:38:57.6002674Z","IpAddress":"127.0.0.1","Culture":"en-US","Url":"/csscsr/blogcommoncss","ShortUrl":"/csscsr/blogcommoncss","Thread":"","LogLevel":"Information","Logger":"Microsoft.AspNetCore.Mvc.Internal.ControllerActionInvoker","Message":"Executed action cloudscribe.SimpleContent.Web.Controllers.csscsrController.blogcommoncss (cloudscribe.SimpleContent.Web) in 41.0641ms","StateJson":"[{\"Key\":\"ActionName\",\"Value\":\"cloudscribe.SimpleContent.Web.Controllers.csscsrController.blogcommoncss (cloudscribe.SimpleContent.Web)\"},{\"Key\":\"ElapsedMilliseconds\",\"Value\":41.0641},{\"Key\":\"{OriginalFormat}\",\"Value\":\"Executed action {ActionName} in {ElapsedMilliseconds}ms\"}]","EventId":2}