{"Id":"59f85b5e-763c-490c-a9b8-11ffda4ffc48","LogDateUtc":"2016-08-30T18:39:05.992056Z","IpAddress":"127.0.0.1","Culture":"en-US","Url":"/csscsr/bootstrapwysiwygjs","ShortUrl":"/csscsr/bootstrapwysiwygjs","Thread":"","LogLevel":"Information","Logger":"Microsoft.AspNetCore.Mvc.Internal.ControllerActionInvoker","Message":"Executed action cloudscribe.SimpleContent.Web.Controllers.csscsrController.bootstrapwysiwygjs (cloudscribe.SimpleContent.Web) in 14.681ms","StateJson":"[{\"Key\":\"ActionName\",\"Value\":\"cloudscribe.SimpleContent.Web.Controllers.csscsrController.bootstrapwysiwygjs (cloudscribe.SimpleContent.Web)\"},{\"Key\":\"ElapsedMilliseconds\",\"Value\":14.681000000000001},{\"Key\":\"{OriginalFormat}\",\"Value\":\"Executed action {ActionName} in {ElapsedMilliseconds}ms\"}]","EventId":2}