{"Id":"665c8b79-5196-48bf-9aba-26d882737cc4","LogDateUtc":"2016-08-30T15:01:21.4217428Z","IpAddress":"127.0.0.1","Culture":"en-US","Url":"/csscsr/bootstrapdatetimepickercss","ShortUrl":"/csscsr/bootstrapdatetimepickercss","Thread":"","LogLevel":"Information","Logger":"Microsoft.AspNetCore.Mvc.Internal.ControllerActionInvoker","Message":"Executing action method cloudscribe.SimpleContent.Web.Controllers.csscsrController.bootstrapdatetimepickercss (cloudscribe.SimpleContent.Web) with arguments () - ModelState is Valid","StateJson":"[{\"Key\":\"ActionName\",\"Value\":\"cloudscribe.SimpleContent.Web.Controllers.csscsrController.bootstrapdatetimepickercss (cloudscribe.SimpleContent.Web)\"},{\"Key\":\"Arguments\",\"Value\":null},{\"Key\":\"ValidationState\",\"Value\":2},{\"Key\":\"{OriginalFormat}\",\"Value\":\"Executing action method {ActionName} with arguments ({Arguments}) - ModelState is {ValidationState}\"}]","EventId":1}