{"Id":"6c0793db-5c8b-4363-840f-5553450a91dc","LogDateUtc":"2016-08-30T19:32:22.4987567Z","IpAddress":"127.0.0.1","Culture":"en-US","Url":"/csscsr/jquerycookie","ShortUrl":"/csscsr/jquerycookie","Thread":"","LogLevel":"Information","Logger":"Microsoft.AspNetCore.Mvc.Internal.ControllerActionInvoker","Message":"Executed action cloudscribe.SimpleContent.Web.Controllers.csscsrController.jquerycookie (cloudscribe.SimpleContent.Web) in 51.9559ms","StateJson":"[{\"Key\":\"ActionName\",\"Value\":\"cloudscribe.SimpleContent.Web.Controllers.csscsrController.jquerycookie (cloudscribe.SimpleContent.Web)\"},{\"Key\":\"ElapsedMilliseconds\",\"Value\":51.9559},{\"Key\":\"{OriginalFormat}\",\"Value\":\"Executed action {ActionName} in {ElapsedMilliseconds}ms\"}]","EventId":2}