{"Id":"79297719-dbdf-4021-bc98-fa6565a12530","LogDateUtc":"2016-08-30T15:03:46.8189815Z","IpAddress":"127.0.0.1","Culture":"en-US","Url":"/csscsr/bootstrapdatetimepickercss","ShortUrl":"/csscsr/bootstrapdatetimepickercss","Thread":"","LogLevel":"Information","Logger":"Microsoft.AspNetCore.Authentication.Cookies.CookieAuthenticationMiddleware","Message":"HttpContext.User merged via AutomaticAuthentication from authenticationScheme: Application-.","StateJson":"[{\"Key\":\"AuthenticationScheme\",\"Value\":\"Application-\"},{\"Key\":\"{OriginalFormat}\",\"Value\":\"HttpContext.User merged via AutomaticAuthentication from authenticationScheme: {AuthenticationScheme}.\"}]","EventId":3}