{"Id":"7b152b84-aab8-4c37-b787-cc1c8257fd54","LogDateUtc":"2016-08-30T15:02:43.8477779Z","IpAddress":"127.0.0.1","Culture":"en-US","Url":"/csscsr/jqueryhotkeys","ShortUrl":"/csscsr/jqueryhotkeys","Thread":"","LogLevel":"Information","Logger":"Microsoft.AspNetCore.Authentication.Cookies.CookieAuthenticationMiddleware","Message":"HttpContext.User merged via AutomaticAuthentication from authenticationScheme: Application-.","StateJson":"[{\"Key\":\"AuthenticationScheme\",\"Value\":\"Application-\"},{\"Key\":\"{OriginalFormat}\",\"Value\":\"HttpContext.User merged via AutomaticAuthentication from authenticationScheme: {AuthenticationScheme}.\"}]","EventId":3}