{"Id":"7ccfef26-7d25-478d-80b4-4c17b6ef8ee1","LogDateUtc":"2016-08-30T15:02:00.440987Z","IpAddress":"127.0.0.1","Culture":"en-US","Url":"/csscsr/bootstrapdatetimepickerjs","ShortUrl":"/csscsr/bootstrapdatetimepickerjs","Thread":"","LogLevel":"Information","Logger":"Microsoft.AspNetCore.Mvc.Internal.ControllerActionInvoker","Message":"Executed action cloudscribe.SimpleContent.Web.Controllers.csscsrController.bootstrapdatetimepickerjs (cloudscribe.SimpleContent.Web) in 21.1023ms","StateJson":"[{\"Key\":\"ActionName\",\"Value\":\"cloudscribe.SimpleContent.Web.Controllers.csscsrController.bootstrapdatetimepickerjs (cloudscribe.SimpleContent.Web)\"},{\"Key\":\"ElapsedMilliseconds\",\"Value\":21.1023},{\"Key\":\"{OriginalFormat}\",\"Value\":\"Executed action {ActionName} in {ElapsedMilliseconds}ms\"}]","EventId":2}