{"Id":"81579d9e-684a-473a-a8db-a76c6ce76264","LogDateUtc":"2016-08-30T15:03:31.4345226Z","IpAddress":"127.0.0.1","Culture":"en-US","Url":"/csscsr/jquerycookie","ShortUrl":"/csscsr/jquerycookie","Thread":"","LogLevel":"Information","Logger":"Microsoft.AspNetCore.Authentication.Cookies.CookieAuthenticationMiddleware","Message":"HttpContext.User merged via AutomaticAuthentication from authenticationScheme: Application-.","StateJson":"[{\"Key\":\"AuthenticationScheme\",\"Value\":\"Application-\"},{\"Key\":\"{OriginalFormat}\",\"Value\":\"HttpContext.User merged via AutomaticAuthentication from authenticationScheme: {AuthenticationScheme}.\"}]","EventId":3}