{"Id":"97443590-0366-4a3c-b68b-0c07c92a81c8","LogDateUtc":"2016-08-30T15:03:33.0387922Z","IpAddress":"127.0.0.1","Culture":"en-US","Url":"/csscsr/editorjs","ShortUrl":"/csscsr/editorjs","Thread":"","LogLevel":"Information","Logger":"Microsoft.AspNetCore.Mvc.Internal.ControllerActionInvoker","Message":"Executed action cloudscribe.SimpleContent.Web.Controllers.csscsrController.editorjs (cloudscribe.SimpleContent.Web) in 38.3172ms","StateJson":"[{\"Key\":\"ActionName\",\"Value\":\"cloudscribe.SimpleContent.Web.Controllers.csscsrController.editorjs (cloudscribe.SimpleContent.Web)\"},{\"Key\":\"ElapsedMilliseconds\",\"Value\":38.3172},{\"Key\":\"{OriginalFormat}\",\"Value\":\"Executed action {ActionName} in {ElapsedMilliseconds}ms\"}]","EventId":2}