{"Id":"bde42666-5d54-4465-bac2-289c11685c4d","LogDateUtc":"2016-08-30T19:49:33.5037504Z","IpAddress":"127.0.0.1","Culture":"en-US","Url":"/csscsr/bootstrapdatetimepickercss","ShortUrl":"/csscsr/bootstrapdatetimepickercss","Thread":"","LogLevel":"Information","Logger":"Microsoft.AspNetCore.Mvc.Internal.ControllerActionInvoker","Message":"Executed action cloudscribe.SimpleContent.Web.Controllers.csscsrController.bootstrapdatetimepickercss (cloudscribe.SimpleContent.Web) in 15.3368ms","StateJson":"[{\"Key\":\"ActionName\",\"Value\":\"cloudscribe.SimpleContent.Web.Controllers.csscsrController.bootstrapdatetimepickercss (cloudscribe.SimpleContent.Web)\"},{\"Key\":\"ElapsedMilliseconds\",\"Value\":15.3368},{\"Key\":\"{OriginalFormat}\",\"Value\":\"Executed action {ActionName} in {ElapsedMilliseconds}ms\"}]","EventId":2}