{"Id":"dbb0137b-9cd6-4bc9-994d-4b82f52f5337","LogDateUtc":"2016-08-30T15:03:22.087613Z","IpAddress":"127.0.0.1","Culture":"en-US","Url":"/csscsr/momentwithlocalesjs","ShortUrl":"/csscsr/momentwithlocalesjs","Thread":"","LogLevel":"Information","Logger":"Microsoft.AspNetCore.Mvc.ContentResult","Message":"Executing ContentResult with HTTP Response ContentType of text/javascript","StateJson":"[{\"Key\":\"ContentType\",\"Value\":\"text/javascript\"},{\"Key\":\"{OriginalFormat}\",\"Value\":\"Executing ContentResult with HTTP Response ContentType of {ContentType}\"}]","EventId":1}