{"Id":"df877945-f3e2-49a0-9e20-34322b977d61","LogDateUtc":"2016-08-30T15:01:23.0015688Z","IpAddress":"127.0.0.1","Culture":"en-US","Url":"/cscsr/jqueryajax","ShortUrl":"/cscsr/jqueryajax","Thread":"","LogLevel":"Information","Logger":"Microsoft.AspNetCore.Mvc.Internal.ControllerActionInvoker","Message":"Executed action cloudscribe.Core.Web.Controllers.cscsrController.jqueryajax (cloudscribe.Core.Web) in 28.5868ms","StateJson":"[{\"Key\":\"ActionName\",\"Value\":\"cloudscribe.Core.Web.Controllers.cscsrController.jqueryajax (cloudscribe.Core.Web)\"},{\"Key\":\"ElapsedMilliseconds\",\"Value\":28.5868},{\"Key\":\"{OriginalFormat}\",\"Value\":\"Executed action {ActionName} in {ElapsedMilliseconds}ms\"}]","EventId":2}