{"Id":"ebcba84f-3611-4582-a577-870dc9521176","LogDateUtc":"2016-08-30T19:49:36.2257481Z","IpAddress":"127.0.0.1","Culture":"en-US","Url":"/csscsr/momentwithlocalesjs","ShortUrl":"/csscsr/momentwithlocalesjs","Thread":"","LogLevel":"Information","Logger":"Microsoft.AspNetCore.Authentication.Cookies.CookieAuthenticationMiddleware","Message":"HttpContext.User merged via AutomaticAuthentication from authenticationScheme: Application-.","StateJson":"[{\"Key\":\"AuthenticationScheme\",\"Value\":\"Application-\"},{\"Key\":\"{OriginalFormat}\",\"Value\":\"HttpContext.User merged via AutomaticAuthentication from authenticationScheme: {AuthenticationScheme}.\"}]","EventId":3}